pyka3005p/__init__.py
pyka3005p/ka3005pserial.py
pyka3005p_tspspi-0.0.5.dist-info/LICENSE.md
pyka3005p_tspspi-0.0.5.dist-info/METADATA
pyka3005p_tspspi-0.0.5.dist-info/WHEEL
pyka3005p_tspspi-0.0.5.dist-info/top_level.txt
pyka3005p_tspspi-0.0.5.dist-info/RECORD
