Metadata-Version: 2.1
Name: pyka3005p-tspspi
Version: 0.0.5
Summary: Korad KA3005P power supply control library (unofficial)
Home-page: https://github.com/tspspi/pyka3005p
Author: Thomas Spielauer
Author-email: pypipackages01@tspi.at
Classifier: Programming Language :: Python :: 3
Classifier: License :: OSI Approved :: BSD License
Classifier: Operating System :: OS Independent
Requires-Python: >=3.6
License-File: LICENSE.md
Requires-Dist: pylabdevs-tspspi (>=0.0.1)
Requires-Dist: pyserial (>=3.5)
